frmdev/__init__.py
frmdev-0.1.0.dist-info/METADATA
frmdev-0.1.0.dist-info/WHEEL
frmdev-0.1.0.dist-info/RECORD
