Metadata-Version: 2.1
Name: frmdev
Version: 0.1.0
Summary: 
Author: Fergal
Author-email: fergal.mullally@gmail.com
Requires-Python: >=3.8,<4.0
Classifier: Programming Language :: Python :: 3
Classifier: Programming Language :: Python :: 3.8
Classifier: Programming Language :: Python :: 3.9
Classifier: Programming Language :: Python :: 3.10
Classifier: Programming Language :: Python :: 3.11
Requires-Dist: black
Requires-Dist: pyflakes
Requires-Dist: pytest (>=5.2,<6.0)
Requires-Dist: pytest-cov
